captchai/__init__.py
captchai/captcha.py
captchai/core/__init__.py
captchai/core/models/__init__.py
captchai/core/models/config.py
captchai/core/models/grid.py
captchai/core/provider/__init__.py
captchai/core/provider/aws/__init__.py
captchai/core/provider/aws/providers.py
captchai/core/provider/aws/resolvers.py
captchai/core/provider/base/__init__.py
captchai/core/provider/base/base.py
captchai-0.0.1.dist-info/METADATA
captchai-0.0.1.dist-info/WHEEL
captchai-0.0.1.dist-info/licenses/LICENSE
captchai-0.0.1.dist-info/RECORD
