Metadata-Version: 2.4
Name: captchai
Version: 0.0.1
Summary: Captchai is a python library for solving captchas using AI
Author-email: Alejandro Jaramillo <me@alejo.co>, xAhai <info@xahai.com>, Alejandro Jaramillo xAhai <alejandro@xahai.co>, Alejandro Jaramillo LaProp <alejandro.jaramillo@laprop.co>, Alejandro Jaramillo TBLabs <alejandro.jaramillo@tblabs.co>
License: MIT License
License-File: LICENSE
Keywords: captcha,captcha solver,captcha solver python,captcha solver python library
Classifier: Development Status :: 4 - Beta
Classifier: Intended Audience :: Developers
Classifier: License :: OSI Approved :: MIT License
Classifier: Operating System :: OS Independent
Classifier: Programming Language :: Python :: 3
Classifier: Programming Language :: Python :: 3.12
Classifier: Topic :: Software Development :: Libraries :: Python Modules
Requires-Python: >=3.12
Requires-Dist: groq>=0.15.0
Requires-Dist: moondream>=0.0.6
Requires-Dist: pydantic>=2.10.5
Requires-Dist: pydub>=0.25.1
Provides-Extra: test
Requires-Dist: bump-my-version>=0.15.4; extra == 'test'
Requires-Dist: pytest>=8.3.4; extra == 'test'
Requires-Dist: python-dotenv>=1.0.1; extra == 'test'
Requires-Dist: ruff>=0.3.0; extra == 'test'
